[null,{"name":"banner","permissions":"NONE","permissions2":"NONE","restriction":"1","_id":"fsnSz","actions":[{"member":"5","varName":"osoba","info":"0","storage":"1","varName2":"banner","name":"Banner"},{"member":"5","varName":"osoba","info":"4","storage":"1","varName2":"kolir","name":"Store Member Info"},{"member":"5","varName":"osoba","info":"2","storage":"1","varName2":"username","name":"Store Member Info"},{"server":"0","varName":"","info":"5","storage":"1","varName2":"avserw","name":"Store Server Info"},{"server":"0","varName":"","info":"2","storage":"1","varName2":"nazwaserw","name":"Store Server Info"},{"storage":"1","varName":"banner","comparison":"1","value":"null","branch":{"iftrue":"3","iffalse":"0","iftrueVal":"2"},"name":"Check Variable"},{"channel":"0","varName":"","message":"","buttons":[],"selectMenus":[],"attachments":[],"embeds":[{"title":"Banner użytkownika ${tempVars(\"username\")}","url":"","color":"RED","timestamp":"true","imageUrl":"${tempVars(\"banner\")}","thumbUrl":"","description":"","fields":[],"author":"","authorUrl":"","authorIcon":"","footerText":"${tempVars(\"nazwaserw\")}","footerIconUrl":"${tempVars(\"avserw\")}"}],"reply":true,"ephemeral":false,"tts":false,"overwrite":false,"dontSend":false,"editMessage":"0","editMessageVarName":"","storage":"0","varName2":"","name":"Send Message"},{"name":"End Action Sequence"},{"channel":"0","varName":"","message":"Niestety ale użytkownik ${slashParams(\"osoba\")} nie posiada banneru..","buttons":[],"selectMenus":[],"attachments":[],"embeds":[],"reply":true,"ephemeral":true,"tts":false,"overwrite":false,"dontSend":false,"editMessage":"0","editMessageVarName":"","storage":"0","varName2":"","name":"Send Message"}],"comType":"4","parameters":[{"name":"osoba","description":"Osoby której chcesz zobaczyc banner!","type":"USER","required":true,"choices":null}],"description":"Banner danej osoby "},{"name":"profil","permissions":"NONE","permissions2":"NONE","restriction":"1","_id":"sEcSc","actions":[{"server":"0","varName":"","info":"5","storage":"1","varName2":"server.icon","name":"Store Server Info"},{"server":"0","varName":"","info":"2","storage":"1","varName2":"server.name","name":"Store Server Info"},{"member":"5","varName":"użytkownik","dataName":"rep-poz","defaultVal":"0","storage":"1","varName2":"rep-poz","name":"Store Member Data"},{"member":"5","varName":"użytkownik","dataName":"ostrzeżenia","defaultVal":"0","storage":"1","varName2":"warny","name":"Store Member Data"},{"member":"5","varName":"użytkownik","dataName":"rep-neg","defaultVal":"0","storage":"1","varName2":"rep-neg","name":"Store Member Data"},{"member":"5","varName":"użytkownik","dataName":"level","defaultVal":"1","storage":"1","varName2":"myLevel","name":"Store Member Data"},{"FirstNumber":"${tempVars(\"rep-poz\")}","info":"0","SecondNumber":"${tempVars(\"rep-neg\")}","storage":"1","varName":"rep-all","name":"Basic Math Operation"},{"member":"5","varName":"użytkownik","info":"16","storage":"1","varName2":"avatar","name":"Store Member Info"},{"member":"5","varName":"użytkownik","info":"31","storage":"1","varName2":"serveravatar","name":"Store Member Info"},{"member":"5","varName":"użytkownik","info":"7","storage":"1","varName2":"ranga","name":"Store Member Info"},{"member":"5","varName":"użytkownik","info":"28","storage":"1","varName2":"flags","name":"Store Member Info"},{"member":"5","varName":"użytkownik","info":"1","storage":"1","varName2":"tag","name":"Store Member Info"},{"member":"5","varName":"użytkownik","info":"22","storage":"1","varName2":"created","name":"Store Member Info"},{"member":"5","varName":"użytkownik","info":"24","storage":"1","varName2":"joined","name":"Store Member Info"},{"member":"5","varName":"użytkownik","info":"0","storage":"1","varName2":"banner","name":"Banner"},{"date":"${tempVars(\"created\")}","info":"2","storage":"1","varName":"created1","name":"Store Date Info"},{"date":"${tempVars(\"joined\")}","info":"2","storage":"1","varName":"joined1","name":"Store Date Info"},{"member":"5","varName":"użytkownik","dataName":"roles","defaultVal":"Nie podano!","storage":"1","varName2":"rangi","name":"Store Member Data"},{"member":"5","varName":"użytkownik","dataName":"badge","defaultVal":"Nie podano!","storage":"1","varName2":"bad","name":"Store Member Data"},{"member":"5","varName":"użytkownik","dataName":"level","defaultVal":"1","storage":"1","varName2":"myLevel","name":"Store Member Data"},{"text":"${tempVars(\"rangi\")}","text2":"false","text3":"[Nie ma cie na serwerze](https://discord.gg/KM5EbpuJcH)","info":"0","storage":"1","varName":"rangaa","name":"Replace Text"},{"text":"${tempVars(\"flags\")}","text2":" ","text3":"Brak!","info":"1","storage":"1","varName":"badgracz","name":"Replace Text"},{"text":"${tempVars(\"ranga\")}","text2":"@everyone","text3":"Brak!","info":"0","storage":"1","varName":"ranga12","name":"Replace Text"},{"text":"${tempVars(\"bad\")}","text2":"false","text3":"Brak!","info":"0","storage":"1","varName":"badge","name":"Replace Text"},{"member":"1","varName":"","info":"1","storage":"1","varName2":"member.id.command","name":"Store Member Info"},{"member":"1","varName":"","info":"2","storage":"1","varName2":"member.username.command","name":"Store Member Info"},{"member":"1","varName":"","info":"16","storage":"1","varName2":"member.avatar.command","name":"Store Member Info"},{"member":"5","varName":"użytkownik","info":"14","storage":"1","varName2":"status3","name":"Store Member Info"},{"text":"${tempVars(\"status3\")}","text2":"undefined","text3":"Brak","info":"0","storage":"1","varName":"tsssssssssssssst","name":"Replace Text"},{"storage":"1","varName":"banner","comparison":"1","value":"undefined","branch":{"iftrue":"2","iffalse":"0","iftrueVal":"33"},"name":"Check Variable"},{"channel":"0","varName":"","message":"","buttons":[],"selectMenus":[],"attachments":[],"embeds":[{"title":"","url":"","color":"RED","timestamp":"false","imageUrl":"${tempVars(\"banner\")}","thumbUrl":"${tempVars(\"avatar\")}","description":"`👤` **Informacje o koncie**\n>  Użytkownik: ${slashParams(\"użytkownik\")}\n>  ID: `${tempVars(\"tag\")}`\n>  Avatar: [Kliknij](${tempVars(\"avatar\")})\n>  Banner: [Kliknij](${tempVars(\"banner\")})\n>  Badge: **${tempVars(\"badgracz\")}**\n>  Data stworzenia konta: <t:${tempVars(\"created1\")}:R>\n>  Data dołączenia na serwer <t:${tempVars(\"joined1\")}:R>\n\n`📋` **Informacje serwerowe:**\n>  Avatar: [Kliknij](${tempVars(\"serveravatar\")})\n>  Rola: ${tempVars(\"ranga12\")}\n>  Ilość warnów: `${tempVars(\"warny\")}`\n>  Ilość reputacji: `${tempVars(\"rep-all\")}`\n>  Reputacja pozytywna: `${tempVars(\"rep-poz\")}`\n>  Reputacja negatywna: `${tempVars(\"rep-neg\")}`\n\n`🎮` **Aktualnie grana gra**\n> ${tempVars(\"tsssssssssssssst\")}\n\n\n","fields":[],"author":"","authorUrl":"","authorIcon":"","footerText":"${tempVars(\"member.username.command\")} (${tempVars(\"member.id.command\")})","footerIconUrl":"${tempVars(\"member.avatar.command\")}"}],"reply":true,"ephemeral":false,"tts":false,"overwrite":false,"dontSend":false,"editMessage":"0","editMessageVarName":"","storage":"0","varName2":"","name":"Send Message"},{"name":"End Action Sequence"},{"channel":"0","varName":"","message":"","buttons":[],"selectMenus":[],"attachments":[],"embeds":[{"title":"","url":"","color":"RED","timestamp":"false","imageUrl":"","thumbUrl":"${tempVars(\"avatar\")}","description":"\n`👤` **Informacje o koncie**\n>  Użytkownik: ${slashParams(\"użytkownik\")}\n>  ID: `${tempVars(\"tag\")}`\n>  Avatar: [Kliknij](${tempVars(\"avatar\")})\n>  Badge: **${tempVars(\"badgracz\")}**\n>  Data stworzenia konta: <t:${tempVars(\"created1\")}:R>\n>  Data dołączenia na serwer <t:${tempVars(\"joined1\")}:R>\n\n`📋` **Informacje serwerowe:**\n>  Avatar: [Kliknij](${tempVars(\"serveravatar\")})\n>  Rola: ${tempVars(\"ranga12\")}\n>  Ilość warnów: `${tempVars(\"warny\")}`\n>  Ilość reputacji: `${tempVars(\"rep-all\")}`\n>  Reputacja pozytywna: `${tempVars(\"rep-poz\")}`\n>  Reputacja negatywna: `${tempVars(\"rep-neg\")}`\n\n`🎮` **Aktualnie grana gra**\n> ${tempVars(\"tsssssssssssssst\")}\n\n","fields":[],"author":"","authorUrl":"","authorIcon":"","footerText":"${tempVars(\"member.username.command\")} (${tempVars(\"member.id.command\")})","footerIconUrl":"${tempVars(\"member.avatar.command\")}"}],"reply":true,"ephemeral":false,"tts":false,"overwrite":false,"dontSend":false,"editMessage":"0","editMessageVarName":"","storage":"0","varName2":"","name":"Send Message"}],"comType":"4","description":"Profil gracza!","parameters":[{"name":"użytkownik","description":"Gracz o którym poznajesz informacje!","type":"USER","required":true,"choices":null}]},{"name":"clear","permissions":"NONE","restriction":"1","_id":"WRITZ","actions":[{"member":"1","varName":"","info":"1","storage":"1","varName2":"author_id","name":"Store Member Info"},{"member":"1","varName":"","info":"21","storage":"1","varName2":"author_tag","name":"Store Member Info"},{"member":"1","varName":"","info":"16","storage":"1","varName2":"author_avatar","name":"Store Member Info"},{"member":"1","varName":"","permission":"MANAGE_MESSAGES","branch":{"iftrue":"2","iffalse":"0","iftrueVal":"7"},"name":"Check Member Permissions"},{"channel":"0","varName":"","message":"","buttons":[],"selectMenus":[],"attachments":[],"embeds":[{"title":"Błąd!","url":"","color":"RED","timestamp":"false","imageUrl":"","thumbUrl":"${tempVars(\"author_avatar\")}","description":"> `❌` Nie masz wystarczających uprawnień!\n> `🔒` Uprawnienie - **ZARZĄDZANIE_WIADOMOŚCIAMI**","fields":[],"author":"","authorUrl":"","authorIcon":"","footerText":"${tempVars(\"author_tag\")} (${tempVars(\"author_id\")})","footerIconUrl":"${tempVars(\"author_avatar\")}"}],"reply":true,"ephemeral":true,"tts":false,"overwrite":false,"dontSend":false,"editMessage":"0","editMessageVarName":"","storage":"0","varName2":"","name":"Send Message"},{"name":"End Action Sequence"},{"storage":"4","varName":"ilosc","comparison":"4","value":"200","branch":{"iftrue":"0","iffalse":"2","iffalseVal":"10"},"name":"Check Variable"},{"channel":"0","varName":"","message":"","buttons":[],"selectMenus":[],"attachments":[],"embeds":[{"title":"Błąd!","url":"","color":"RED","timestamp":"false","imageUrl":"","thumbUrl":"${tempVars(\"author_avatar\")}","description":"> `❌` Nie możesz usunąć więcej niż 200 wiadomości!","fields":[],"author":"","authorUrl":"","authorIcon":"","footerText":"${tempVars(\"author_tag\")} (${tempVars(\"author_id\")})","footerIconUrl":"${tempVars(\"author_avatar\")}"}],"reply":true,"ephemeral":true,"tts":false,"overwrite":false,"dontSend":false,"editMessage":"0","editMessageVarName":"","storage":"0","varName2":"","name":"Send Message"},{"name":"End Action Sequence"},{"storage":"4","varName":"ilosc","comparison":"3","value":"1","branch":{"iftrue":"0","iffalse":"2","iffalseVal":"13"},"name":"Check Variable"},{"channel":"0","varName":"","message":"","buttons":[],"selectMenus":[],"attachments":[],"embeds":[{"title":"Błąd!","url":"","color":"RED","timestamp":"false","imageUrl":"","thumbUrl":"${tempVars(\"author_avatar\")}","description":"> `❌` Musisz usunąć więcej niż jedną wiadomość!","fields":[],"author":"","authorUrl":"","authorIcon":"","footerText":"${tempVars(\"author_tag\")} (${tempVars(\"author_id\")})","footerIconUrl":"${tempVars(\"author_avatar\")}"}],"reply":true,"ephemeral":true,"tts":false,"overwrite":false,"dontSend":false,"editMessage":"0","editMessageVarName":"","storage":"0","varName2":"","name":"Send Message"},{"name":"End Action Sequence"},{"channel":"0","count":"${slashParams(\"ilosc\")}","condition":"0","custom":"","varName":"","name":"Delete Bulk Messages"},{"channel":"0","varName":"","message":"","buttons":[],"selectMenus":[],"attachments":[],"embeds":[{"title":"Usunięto wiadomości!","url":"","color":"RED","timestamp":"false","imageUrl":"","thumbUrl":"${tempVars(\"author_avatar\")}","description":"","fields":[{"name":"`📛` Administrator:","value":"> ${member}・${tempVars(\"author_tag\")}","inline":"false"},{"name":"`🗑️` Ilość:","value":"> `${slashParams(\"ilosc\")}`","inline":"false"}],"author":"","authorUrl":"","authorIcon":"","footerText":"${tempVars(\"author_tag\")} (${tempVars(\"author_id\")})","footerIconUrl":"${tempVars(\"author_avatar\")}"}],"reply":true,"ephemeral":false,"tts":false,"overwrite":false,"dontSend":false,"editMessage":"0","editMessageVarName":"","storage":"1","varName2":"embed_time","name":"Send Message"},{"time":"5","measurement":"1","name":"Wait"},{"storage":"1","varName":"embed_time","reason":"","name":"Delete Message"}],"comType":"4","parameters":[{"name":"ilosc","description":"Wybierz ilość wiadomości do usunięcia!","type":"INTEGER","required":true,"choices":null}],"description":"Usuwa wybraną ilość wiadomości z kanału!"},{"name":"ogloszenie","permissions":"NONE","permissions2":"NONE","restriction":"1","_id":"pfcIL","actions":[{"member":"1","varName":"","info":"1","storage":"1","varName2":"author_id","name":"Store Member Info"},{"member":"1","varName":"","info":"21","storage":"1","varName2":"author_tag","name":"Store Member Info"},{"member":"1","varName":"","info":"16","storage":"1","varName2":"author_avatar","name":"Store Member Info"},{"member":"1","varName":"","permission":"MANAGE_MESSAGES","branch":{"iftrue":"2","iffalse":"0","iftrueVal":"7"},"name":"Check Member Permissions"},{"channel":"0","varName":"","message":"","buttons":[],"selectMenus":[],"attachments":[],"embeds":[{"title":"Błąd!","url":"","color":"RED","timestamp":"false","imageUrl":"","thumbUrl":"${tempVars(\"author_avatar\")}","description":"> `❌` Nie masz wystarczających uprawnień!\n> `🔒` Uprawnienie - **ZARZĄDZANIE_WIADOMOŚCIAMI**","fields":[],"author":"","authorUrl":"","authorIcon":"","footerText":"${tempVars(\"author_tag\")} (${tempVars(\"author_id\")})","footerIconUrl":"${tempVars(\"author_avatar\")}"}],"reply":true,"ephemeral":true,"tts":false,"overwrite":false,"dontSend":false,"editMessage":"0","editMessageVarName":"","storage":"0","varName2":"","name":"Send Message"},{"name":"End Action Sequence"},{"channel":"8","varName":"kanal","message":"","buttons":[],"selectMenus":[],"attachments":[],"embeds":[{"title":"Nowe ogłoszenie: ${slashParams(\"tytul\")}","url":"","color":"RED","timestamp":"true","imageUrl":"","thumbUrl":"${tempVars(\"author_avatar\")}","description":"","fields":[{"name":"`📛` Administrator:","value":"> ${member}・${tempVars(\"author_tag\")}","inline":"false"},{"name":"`📋` Treść:","value":"> ${slashParams(\"tresc\")}","inline":"false"}],"author":"","authorUrl":"","authorIcon":"","footerText":"${tempVars(\"author_tag\")} (${tempVars(\"author_id\")})","footerIconUrl":"${tempVars(\"author_avatar\")}"}],"reply":true,"ephemeral":false,"tts":false,"overwrite":false,"dontSend":false,"editMessage":"0","editMessageVarName":"","storage":"0","varName2":"","name":"Send Message"},{"channel":"0","varName":"","message":"Pomyślnie wysłano ogłoszenie na ${slashParams(\"kanal\")}","buttons":[],"selectMenus":[],"attachments":[],"embeds":[],"reply":true,"ephemeral":true,"tts":false,"overwrite":false,"dontSend":false,"editMessage":"0","editMessageVarName":"","storage":"0","varName2":"","name":"Send Message"}],"comType":"4","parameters":[{"name":"kanal","description":"Wybierz kanał na który ma wysłać się ogłoszenie!","type":"CHANNEL","required":true,"choices":null},{"name":"tytul","description":"Podaj tytuał ogłoszenia!","type":"STRING","required":true,"choices":null},{"name":"tresc","description":"Podaj treść ogłoszenia!","type":"STRING","required":true,"choices":null}],"description":"Wyślij ogłoszenie na dany kanał!"},{"name":"warns","permissions":"NONE","permissions2":"NONE","restriction":"1","_id":"eqNNA","actions":[{"member":"1","varName":"","info":"1","storage":"1","varName2":"author_id","name":"Store Member Info"},{"member":"1","varName":"","info":"21","storage":"1","varName2":"author_tag","name":"Store Member Info"},{"member":"1","varName":"","info":"16","storage":"1","varName2":"author_avatar","name":"Store Member Info"},{"server":"0","varName":"","info":"2","storage":"1","varName2":"server_name","name":"Store Server Info"},{"member":"1","varName":"","dataName":"ostrzeżenia","defaultVal":"0","storage":"1","varName2":"ostrzeżenia_variable","name":"Store Member Data"},{"channel":"0","varName":"","message":"","buttons":[],"selectMenus":[],"attachments":[],"embeds":[{"title":"Twoje statystyki ostrzeżeń!","url":"","color":"RED","timestamp":"false","imageUrl":"","thumbUrl":"${tempVars(\"author_avatar\")}","description":"","fields":[{"name":"`❓` Ilość ostrzeżeń:","value":"> `${tempVars(\"ostrzeżenia_variable\")}`","inline":"false"},{"name":"`🔗` Serwer:","value":"> `${tempVars(\"server_name\")}`","inline":"false"}],"author":"","authorUrl":"","authorIcon":"","footerText":"${tempVars(\"author_tag\")} (${tempVars(\"author_id\")})","footerIconUrl":"${tempVars(\"author_avatar\")}"}],"reply":true,"ephemeral":true,"tts":false,"overwrite":false,"dontSend":false,"editMessage":"0","editMessageVarName":"","storage":"0","varName2":"","name":"Send Message"}],"comType":"4","description":"Sprawdza ilość ostrzeżeń!"},{"name":"warn","permissions":"NONE","permissions2":"NONE","restriction":"1","_id":"ALHqi","actions":[{"member":"1","varName":"","info":"1","storage":"1","varName2":"author_id","name":"Store Member Info"},{"member":"1","varName":"","info":"21","storage":"1","varName2":"author_tag","name":"Store Member Info"},{"member":"1","varName":"","info":"16","storage":"1","varName2":"author_avatar","name":"Store Member Info"},{"member":"1","varName":"","permission":"BAN_MEMBERS","branch":{"iftrue":"2","iffalse":"0","iftrueVal":"7"},"name":"Check Member Permissions"},{"channel":"0","varName":"","message":"","buttons":[],"selectMenus":[],"attachments":[],"embeds":[{"title":"Błąd!","url":"","color":"RED","timestamp":"false","imageUrl":"","thumbUrl":"${tempVars(\"author_avatar\")}","description":"> `❌` Nie masz wystarczających uprawnień!\n> `🔒` Uprawnienie - **BANOWANIE_CZŁONKÓW**","fields":[],"author":"","authorUrl":"","authorIcon":"","footerText":"${tempVars(\"author_tag\")} (${tempVars(\"author_id\")})","footerIconUrl":"${tempVars(\"author_avatar\")}"}],"reply":true,"ephemeral":true,"tts":false,"overwrite":false,"dontSend":false,"editMessage":"0","editMessageVarName":"","storage":"0","varName2":"","name":"Send Message"},{"name":"End Action Sequence"},{"member":"5","varName":"uzytkownik","permission":"ADMINISTRATOR","branch":{"iftrue":"0","iffalse":"2","iffalseVal":"10"},"name":"Check Member Permissions"},{"channel":"0","varName":"","message":"","buttons":[],"selectMenus":[],"attachments":[],"embeds":[{"title":"Błąd!","url":"","color":"RED","timestamp":"false","imageUrl":"","thumbUrl":"${tempVars(\"author_avatar\")}","description":"> `❌` Nie możesz nadać ostrzeżenia Administratorowi!","fields":[],"author":"","authorUrl":"","authorIcon":"","footerText":"${tempVars(\"author_tag\")} (${tempVars(\"author_id\")})","footerIconUrl":"${tempVars(\"author_avatar\")}"}],"reply":true,"ephemeral":true,"tts":false,"overwrite":false,"dontSend":false,"editMessage":"0","editMessageVarName":"","storage":"0","varName2":"","name":"Send Message"},{"name":"End Action Sequence"},{"member":"5","varName":"uzytkownik","info":"1","storage":"1","varName2":"mention_id","name":"Store Member Info"},{"member":"5","varName":"uzytkownik","info":"21","storage":"1","varName2":"mention_tag","name":"Store Member Info"},{"member":"5","varName":"uzytkownik","info":"16","storage":"1","varName2":"mention_avatar","name":"Store Member Info"},{"server":"0","varName":"","info":"2","storage":"1","varName2":"server_name","name":"Store Server Info"},{"member":"5","varName":"uzytkownik","dataName":"ostrzeżenia","changeType":"1","value":"1","name":"Control Member Data"},{"channel":"0","varName":"","message":"","buttons":[],"selectMenus":[],"attachments":[],"embeds":[{"title":"Ostrzeżono użytkownika!","url":"","color":"RED","timestamp":"false","imageUrl":"","thumbUrl":"${tempVars(\"mention_avatar\")}","description":"","fields":[{"name":"`📛` Administrator:","value":"> ${member}・${tempVars(\"author_tag\")}","inline":"false"},{"name":"`👤` Użytkownik","value":"> ${slashParams(\"uzytkownik\")}・${tempVars(\"mention_tag\")}","inline":"false"},{"name":"`📋` Powód:","value":"> ${slashParams(\"powod\")}","inline":"false"}],"author":"","authorUrl":"","authorIcon":"","footerText":"${tempVars(\"mention_tag\")} (${tempVars(\"mention_id\")})","footerIconUrl":"${tempVars(\"mention_avatar\")}"}],"reply":true,"ephemeral":false,"tts":false,"overwrite":false,"dontSend":false,"editMessage":"0","editMessageVarName":"","storage":"0","varName2":"","name":"Send Message"},{"channel":"8","varName":"uzytkownik","message":"","buttons":[],"selectMenus":[],"attachments":[],"embeds":[{"title":"Zostałeś/aś ostrzeżony/a!","url":"","color":"RED","timestamp":"false","imageUrl":"","thumbUrl":"${tempVars(\"author_avatar\")}","description":"","fields":[{"name":"`📛` Administrator:","value":"> ${member}・${tempVars(\"author_tag\")}","inline":"false"},{"name":"`👤` Użytkownik","value":"> ${slashParams(\"uzytkownik\")}・${tempVars(\"mention_tag\")}","inline":"false"},{"name":"`🔗` Serwer:","value":"> `${tempVars(\"server_name\")}`","inline":"false"},{"name":"`📋` Powód:","value":"> ${slashParams(\"powod\")}","inline":"false"}],"author":"","authorUrl":"","authorIcon":"","footerText":"${tempVars(\"author_tag\")} (${tempVars(\"author_id\")})","footerIconUrl":"${tempVars(\"author_avatar\")}"}],"reply":true,"ephemeral":false,"tts":false,"overwrite":false,"dontSend":false,"editMessage":"0","editMessageVarName":"","storage":"0","varName2":"","name":"Send Message"},{"member":"5","varName":"uzytkownik","dataName":"ostrzeżenia","comparison":"1","value":"'3'","branch":{"iftrue":"0","iffalse":"2","iffalseVal":"21"},"name":"Check Member Data"},{"channel":"8","varName":"uzytkownik","message":"","buttons":[],"selectMenus":[],"attachments":[],"embeds":[{"title":"Zostałeś/aś wyrzucony/a!","url":"","color":"RED","timestamp":"false","imageUrl":"","thumbUrl":"${tempVars(\"author_avatar\")}","description":"","fields":[{"name":"`👤` Użytkownik","value":"> ${slashParams(\"uzytkownik\")}・${tempVars(\"mention_tag\")}","inline":"false"},{"name":"`🔗` Serwer:","value":"> `${tempVars(\"server_name\")}`","inline":"false"},{"name":"`📋` Powód:","value":"> `Automatyczne wyrzucenie - 3 ostrzeżenia.`","inline":"false"}],"author":"","authorUrl":"","authorIcon":"","footerText":"${tempVars(\"author_tag\")} (${tempVars(\"author_id\")})","footerIconUrl":"${tempVars(\"author_avatar\")}"}],"reply":true,"ephemeral":false,"tts":false,"overwrite":false,"dontSend":false,"editMessage":"0","editMessageVarName":"","storage":"0","varName2":"","name":"Send Message"},{"member":"5","varName":"uzytkownik","reason":"","name":"Kick Member"},{"name":"End Action Sequence"},{"member":"5","varName":"uzytkownik","dataName":"ostrzeżenia","comparison":"1","value":"'6'","branch":{"iftrue":"0","iffalse":"1"},"name":"Check Member Data"},{"channel":"8","varName":"uzytkownik","message":"","buttons":[],"selectMenus":[],"attachments":[],"embeds":[{"title":"Zostałeś/aś zbanowany/a!","url":"","color":"RED","timestamp":"false","imageUrl":"","thumbUrl":"${tempVars(\"author_avatar\")}","description":"","fields":[{"name":"`👤` Użytkownik","value":"> ${slashParams(\"uzytkownik\")}・${tempVars(\"mention_tag\")}","inline":"false"},{"name":"`🔗` Serwer:","value":"> `${tempVars(\"server_name\")}`","inline":"false"},{"name":"`📋` Powód:","value":"> `Automatyczny ban - 6 ostrzeżeń.`","inline":"false"}],"author":"","authorUrl":"","authorIcon":"","footerText":"${tempVars(\"author_tag\")} (${tempVars(\"author_id\")})","footerIconUrl":"${tempVars(\"author_avatar\")}"}],"reply":true,"ephemeral":false,"tts":false,"overwrite":false,"dontSend":false,"editMessage":"0","editMessageVarName":"","storage":"0","varName2":"","name":"Send Message"},{"member":"5","varName":"uzytkownik","reason":"","days":"","name":"Ban Member"}],"comType":"4","description":"Ostrzega użytkownika!","parameters":[{"name":"uzytkownik","description":"Użytkownik któremu chcesz nadać ostrzeżenie!","type":"USER","required":true,"choices":null},{"name":"powod","description":"Powód ostrzeżenia!","type":"STRING","required":true,"choices":null}]},{"name":"removerole","permissions":"NONE","permissions2":"NONE","restriction":"1","_id":"MokbF","actions":[{"member":"1","varName":"","info":"1","storage":"1","varName2":"author_id","name":"Store Member Info"},{"member":"1","varName":"","info":"16","storage":"1","varName2":"author_avatar","name":"Store Member Info"},{"member":"1","varName":"","info":"21","storage":"1","varName2":"author_tag","name":"Store Member Info"},{"member":"1","varName":"","permission":"MANAGE_ROLES","branch":{"iftrue":"2","iffalse":"0","iftrueVal":"7"},"name":"Check Member Permissions"},{"channel":"0","varName":"","message":"","buttons":[],"selectMenus":[],"attachments":[],"embeds":[{"title":"Błąd!","url":"","color":"RED","timestamp":"false","imageUrl":"","thumbUrl":"${tempVars(\"author_avatar\")}","description":"> `❌` Nie masz wystarczających uprawnień!\n> `🔒` Uprawnienie - **ZARZĄDZANIE_ROLAMI**","fields":[],"author":"","authorUrl":"","authorIcon":"","footerText":"${tempVars(\"author_tag\")} (${tempVars(\"author_id\")})","footerIconUrl":"${tempVars(\"author_avatar\")}"}],"reply":true,"ephemeral":true,"tts":false,"overwrite":false,"dontSend":false,"editMessage":"0","editMessageVarName":"","storage":"0","varName2":"","name":"Send Message"},{"name":"End Action Sequence"},{"member":"5","varName":"uzytkownik","role":"6","varName2":"rola","branch":{"iftrue":"2","iffalse":"0","iftrueVal":"10"},"name":"Check If Member has Role"},{"channel":"0","varName":"","message":"","buttons":[],"selectMenus":[],"attachments":[],"embeds":[{"title":"Błąd!","url":"","color":"RED","timestamp":"false","imageUrl":"","thumbUrl":"${tempVars(\"author_avatar\")}","description":"> `❌` Ten użytkownik nie posiada oznaczonej roli.","fields":[],"author":"","authorUrl":"","authorIcon":"","footerText":"${tempVars(\"author_tag\")} (${tempVars(\"author_id\")})","footerIconUrl":"${tempVars(\"author_avatar\")}"}],"reply":true,"ephemeral":true,"tts":false,"overwrite":false,"dontSend":false,"editMessage":"0","editMessageVarName":"","storage":"0","varName2":"","name":"Send Message"},{"name":"End Action Sequence"},{"member":"5","varName":"uzytkownik","info":"1","storage":"1","varName2":"mention_id","name":"Store Member Info"},{"member":"5","varName":"uzytkownik","info":"16","storage":"1","varName2":"mention_avatar","name":"Store Member Info"},{"member":"5","varName":"uzytkownik","info":"21","storage":"1","varName2":"mention_tag","name":"Store Member Info"},{"role":"6","varName":"rola","info":"2","storage":"1","varName2":"role_name","name":"Store Role Info"},{"member":"5","varName2":"uzytkownik","role":"6","varName":"rola","reason":"","name":"Remove Member Role"},{"channel":"0","varName":"","message":"","buttons":[],"selectMenus":[],"attachments":[],"embeds":[{"title":"Poprawnie odebrano role!","url":"","color":"RED","timestamp":"false","imageUrl":"","thumbUrl":"${tempVars(\"author_avatar\")}","description":"","fields":[{"name":"`📛` Administrator:","value":"> ${member}・${tempVars(\"author_tag\")}","inline":"false"},{"name":"`👤` Użytkownik:","value":"> ${slashParams(\"uzytkownik\")}・${tempVars(\"mention_tag\")}","inline":"false"},{"name":"`🔧` Rola: ","value":"> ${slashParams(\"rola\")}・${tempVars(\"role_name\")}","inline":"false"}],"author":"","authorUrl":"","authorIcon":"","footerText":"${tempVars(\"mention_tag\")} (${tempVars(\"mention_id\")})","footerIconUrl":"${tempVars(\"mention_avatar\")}"}],"reply":true,"ephemeral":false,"tts":false,"overwrite":false,"dontSend":false,"editMessage":"0","editMessageVarName":"","storage":"0","varName2":"","name":"Send Message"}],"comType":"4","description":"Odbiera role użytkwonikowi!","parameters":[{"name":"uzytkownik","description":"Użytkownik któremu chcesz odebrać role!","type":"USER","required":true,"choices":null},{"name":"rola","description":"Rola którą chcesz odebrać!","type":"ROLE","required":true,"choices":null}]},{"name":"kick","permissions":"NONE","permissions2":"NONE","restriction":"1","_id":"xtzbv","actions":[{"member":"1","varName":"","info":"1","storage":"1","varName2":"author_id","name":"Store Member Info"},{"member":"1","varName":"","info":"21","storage":"1","varName2":"author_tag","name":"Store Member Info"},{"member":"1","varName":"","info":"16","storage":"1","varName2":"author_avatar","name":"Store Member Info"},{"member":"1","varName":"","permission":"KICK_MEMBERS","branch":{"iftrue":"2","iffalse":"0","iftrueVal":"7"},"name":"Check Member Permissions"},{"channel":"0","varName":"","message":"","buttons":[],"selectMenus":[],"attachments":[],"embeds":[{"title":"Błąd!","url":"","color":"RED","timestamp":"false","imageUrl":"","thumbUrl":"${tempVars(\"author_avatar\")}","description":"> `❌` Nie masz wystarczających uprawnień!\n> `🔒` Uprawnienie - **WYRZUCANIE_CZŁONKÓW**","fields":[],"author":"","authorUrl":"","authorIcon":"","footerText":"${tempVars(\"author_tag\")} (${tempVars(\"author_id\")})","footerIconUrl":"${tempVars(\"author_avatar\")}"}],"reply":true,"ephemeral":true,"tts":false,"overwrite":false,"dontSend":false,"editMessage":"0","editMessageVarName":"","storage":"0","varName2":"","name":"Send Message"},{"name":"End Action Sequence"},{"member":"5","varName":"uzytkownik","permission":"ADMINISTRATOR","branch":{"iftrue":"0","iffalse":"2","iffalseVal":"12"},"name":"Check Member Permissions"},{"channel":"0","varName":"","message":"","buttons":[],"selectMenus":[],"attachments":[],"embeds":[{"title":"Błąd!","url":"","color":"RED","timestamp":"false","imageUrl":"","thumbUrl":"${tempVars(\"author_avatar\")}","description":"> `❌` Nie możesz wyrzucić administratora!","fields":[],"author":"","authorUrl":"","authorIcon":"","footerText":"${tempVars(\"author_tag\")} (${tempVars(\"author_id\")})","footerIconUrl":"${tempVars(\"author_avatar\")}"}],"reply":true,"ephemeral":true,"tts":false,"overwrite":false,"dontSend":false,"editMessage":"0","editMessageVarName":"","storage":"0","varName2":"","name":"Send Message"},{"name":"End Action Sequence"},{"member":"5","varName":"uzytkownik","info":"1","storage":"1","varName2":"mention_id","name":"Store Member Info"},{"member":"5","varName":"uzytkownik","info":"16","storage":"1","varName2":"mention_avatar","name":"Store Member Info"},{"member":"5","varName":"uzytkownik","info":"21","storage":"1","varName2":"mention_tag","name":"Store Member Info"},{"server":"0","varName":"","info":"2","storage":"1","varName2":"server_name","name":"Store Server Info"},{"channel":"8","varName":"uzytkownik","message":"","buttons":[],"selectMenus":[],"attachments":[],"embeds":[{"title":"Zostałeś/aś wyrzucony/a!","url":"","color":"RED","timestamp":"false","imageUrl":"","thumbUrl":"${tempVars(\"author_avatar\")}","description":"","fields":[{"name":"`📛` Administrator:","value":"> ${member}・${tempVars(\"author_tag\")}","inline":"false"},{"name":"`👤` Użytkownik:","value":"> ${slashParams(\"uzytkownik\")}・${tempVars(\"mention_tag\")}","inline":"false"},{"name":"`🔗` Serwer:","value":"> `${tempVars(\"server_name\")}`","inline":"false"},{"name":"`📋` Powód:","value":"> ${slashParams(\"powod\")}","inline":"false"}],"author":"","authorUrl":"","authorIcon":"","footerText":"${tempVars(\"author_tag\")} (${tempVars(\"author_id\")})","footerIconUrl":"${tempVars(\"author_avatar\")}"}],"reply":true,"ephemeral":false,"tts":false,"overwrite":false,"dontSend":false,"editMessage":"0","editMessageVarName":"","storage":"0","varName2":"","name":"Send Message"},{"member":"5","varName":"uzytkownik","reason":"${slashParams(\"powod\")}","name":"Kick Member"},{"channel":"0","varName":"uzytkownik","message":"","buttons":[],"selectMenus":[],"attachments":[],"embeds":[{"title":"Wyrzucono użytkownika!","url":"","color":"RED","timestamp":"false","imageUrl":"","thumbUrl":"${tempVars(\"author_avatar\")}","description":"","fields":[{"name":"`📛` Administrator:","value":"> ${member}・${tempVars(\"author_tag\")}","inline":"false"},{"name":"`👤` Użytkownik:","value":"> ${slashParams(\"uzytkownik\")}・${tempVars(\"mention_tag\")}","inline":"false"},{"name":"`📋` Powód:","value":"> ${slashParams(\"powod\")}","inline":"false"}],"author":"","authorUrl":"","authorIcon":"","footerText":"${tempVars(\"author_tag\")} (${tempVars(\"author_id\")})","footerIconUrl":"${tempVars(\"author_avatar\")}"}],"reply":true,"ephemeral":false,"tts":false,"overwrite":false,"dontSend":false,"editMessage":"0","editMessageVarName":"","storage":"0","varName2":"","name":"Send Message"}],"comType":"4","parameters":[{"name":"uzytkownik","description":"Użytkownik którego chcesz wyrzucić!","type":"USER","required":true,"choices":null},{"name":"powod","description":"Powód wyrzucenia!","type":"STRING","required":true,"choices":null}],"description":"Wyrzuca użytkownika z serwera!"},{"name":"ban","permissions":"NONE","permissions2":"NONE","restriction":"1","_id":"xANab","actions":[{"member":"1","varName":"","info":"1","storage":"1","varName2":"author_id","name":"Store Member Info"},{"member":"1","varName":"","info":"21","storage":"1","varName2":"author_tag","name":"Store Member Info"},{"member":"1","varName":"","info":"16","storage":"1","varName2":"author_avatar","name":"Store Member Info"},{"member":"1","varName":"","permission":"BAN_MEMBERS","branch":{"iftrue":"2","iffalse":"0","iftrueVal":"7"},"name":"Check Member Permissions"},{"channel":"0","varName":"","message":"","buttons":[],"selectMenus":[],"attachments":[],"embeds":[{"title":"Błąd!","url":"","color":"RED","timestamp":"false","imageUrl":"","thumbUrl":"${tempVars(\"author_avatar\")}","description":"> `❌` Nie masz wystarczających uprawnień!\n> `🔒` Uprawnienie - **BANOWANIE_CZŁONKÓW**","fields":[],"author":"","authorUrl":"","authorIcon":"","footerText":"${tempVars(\"author_tag\")} (${tempVars(\"author_id\")})","footerIconUrl":"${tempVars(\"author_avatar\")}"}],"reply":true,"ephemeral":true,"tts":false,"overwrite":false,"dontSend":false,"editMessage":"0","editMessageVarName":"","storage":"0","varName2":"","name":"Send Message"},{"name":"End Action Sequence"},{"member":"5","varName":"uzytkownik","permission":"ADMINISTRATOR","branch":{"iftrue":"0","iffalse":"2","iffalseVal":"10"},"name":"Check Member Permissions"},{"channel":"0","varName":"","message":"","buttons":[],"selectMenus":[],"attachments":[],"embeds":[{"title":"Błąd!","url":"","color":"RED","timestamp":"false","imageUrl":"","thumbUrl":"${tempVars(\"author_avatar\")}","description":"> `❌` Nie możesz zbanować administratora!","fields":[],"author":"","authorUrl":"","authorIcon":"","footerText":"${tempVars(\"author_tag\")} (${tempVars(\"author_id\")})","footerIconUrl":"${tempVars(\"author_avatar\")}"}],"reply":true,"ephemeral":true,"tts":false,"overwrite":false,"dontSend":false,"editMessage":"0","editMessageVarName":"","storage":"0","varName2":"","name":"Send Message"},{"name":"End Action Sequence"},{"member":"5","varName":"uzytkownik","info":"1","storage":"1","varName2":"mention_id","name":"Store Member Info"},{"member":"5","varName":"uzytkownik","info":"16","storage":"1","varName2":"mention_avatar","name":"Store Member Info"},{"member":"5","varName":"uzytkownik","info":"21","storage":"1","varName2":"mention_tag","name":"Store Member Info"},{"server":"0","varName":"","info":"2","storage":"1","varName2":"server_name","name":"Store Server Info"},{"channel":"8","varName":"uzytkownik","message":"","buttons":[],"selectMenus":[],"attachments":[],"embeds":[{"title":"Zostałeś/aś zbanowany/a!","url":"","color":"RED","timestamp":"false","imageUrl":"","thumbUrl":"${tempVars(\"author_avatar\")}","description":"","fields":[{"name":"`📛` Administrator:","value":"> ${member}・${tempVars(\"author_tag\")}","inline":"false"},{"name":"`👤` Użytkownik:","value":"> ${slashParams(\"uzytkownik\")}・${tempVars(\"mention_tag\")}","inline":"false"},{"name":"`🔗` Serwer:","value":"> `${tempVars(\"server_name\")}`","inline":"false"},{"name":"`📋` Powód:","value":"> ${slashParams(\"powod\")}","inline":"false"}],"author":"","authorUrl":"","authorIcon":"","footerText":"${tempVars(\"author_tag\")} (${tempVars(\"author_id\")})","footerIconUrl":"${tempVars(\"author_avatar\")}"}],"reply":true,"ephemeral":false,"tts":false,"overwrite":false,"dontSend":false,"editMessage":"0","editMessageVarName":"","storage":"0","varName2":"","name":"Send Message"},{"member":"5","varName":"uzytkownik","reason":"${slashParams(\"powod\")}","days":"","name":"Ban Member"},{"channel":"0","varName":"uzytkownik","message":"","buttons":[],"selectMenus":[],"attachments":[],"embeds":[{"title":"Zbanowano użytkownika!","url":"","color":"RED","timestamp":"false","imageUrl":"","thumbUrl":"${tempVars(\"author_avatar\")}","description":"","fields":[{"name":"`📛` Administrator:","value":"> ${member}・${tempVars(\"author_tag\")}","inline":"false"},{"name":"`👤` Użytkownik:","value":"> ${slashParams(\"uzytkownik\")}・${tempVars(\"mention_tag\")}","inline":"false"},{"name":"`📋` Powód:","value":"> ${slashParams(\"powod\")}","inline":"false"}],"author":"","authorUrl":"","authorIcon":"","footerText":"${tempVars(\"author_tag\")} (${tempVars(\"author_id\")})","footerIconUrl":"${tempVars(\"author_avatar\")}"}],"reply":true,"ephemeral":false,"tts":false,"overwrite":false,"dontSend":false,"editMessage":"0","editMessageVarName":"","storage":"0","varName2":"","name":"Send Message"}],"comType":"4","parameters":[{"name":"uzytkownik","description":"Użytkownik którego chcesz zbanować!","type":"USER","required":true,"choices":null},{"name":"powod","description":"Powód bana!","type":"STRING","required":true,"choices":null}],"description":"Banuje użytkownika na serwerze!"},{"name":"unban","permissions":"NONE","permissions2":"NONE","restriction":"1","_id":"dtbAq","actions":[{"member":"101","varName":"${slashParams(\"id\")}","reason":"","name":"Unban Member"},{"channel":"0","varName":"","message":"","buttons":[],"selectMenus":[],"attachments":[],"embeds":[{"title":"Unban","url":"","color":"RED","timestamp":"false","imageUrl":"","thumbUrl":"","description":"Administrator ${member}, Odbanował <@${slashParams(\"id\")}>","fields":[],"author":"","authorUrl":"","authorIcon":"","footerText":"","footerIconUrl":""}],"reply":true,"ephemeral":false,"tts":false,"overwrite":false,"dontSend":false,"editMessage":"0","editMessageVarName":"","storage":"0","varName2":"","name":"Send Message"}],"comType":"4","parameters":[{"name":"id","description":"Id osoby która chcesz odbanować","type":"STRING","required":true,"choices":null}],"description":"Odbanuj osobę"},{"name":"warnlist","permissions":"NONE","permissions2":"NONE","restriction":"1","_id":"EtNxl","actions":[{"debu":"1","numbefst2":")","numbefstselect":"2","sort":"1","start":"username","middle":"-","end":"result","getresults":"","dataName":"ostrzeżenia","varName2":"warny","storage":"1","name":"Store Member Data List"},{"channel":"0","varName":"","message":"","buttons":[],"selectMenus":[],"attachments":[],"embeds":[{"title":"","url":"","color":"RED","timestamp":"false","imageUrl":"https://cdn.discordapp.com/attachments/949657883941961789/956268544499286126/miniaturka_warny_uzytkownikow.jpg","thumbUrl":"","description":"**lista warnów użytkowników** \n\n${tempVars(\"warny\")} ","fields":[],"author":"","authorUrl":"","authorIcon":"","footerText":"","footerIconUrl":""}],"reply":true,"ephemeral":false,"tts":false,"overwrite":false,"dontSend":false,"editMessage":"0","editMessageVarName":"","storage":"0","varName2":"","name":"Send Message"}],"comType":"4","description":"Lista warnów użytkowników"},{"name":"restart","temp":"","event-type":"48","_id":"blXly","actions":[{"member":"1","varName":"","info":"6","varName2":"","iftrue":"2","iftrueVal":"4","iffalse":"0","iffalseVal":"4","name":"Check If Member"},{"channel":"0","varName":"","message":"","buttons":[],"selectMenus":[],"attachments":[],"embeds":[{"title":"Niestety...","url":"","color":"RED","timestamp":"false","imageUrl":"","thumbUrl":"","description":"Tej komendy może używać tylko właściciel bota","fields":[],"author":"","authorUrl":"","authorIcon":"","footerText":"","footerIconUrl":""}],"reply":true,"ephemeral":true,"tts":false,"overwrite":false,"dontSend":false,"editMessage":"0","editMessageVarName":"","storage":"0","varName2":"","name":"Send Message"},{"name":"End Action Sequence"},{"channel":"0","varName":"","message":"","buttons":[],"selectMenus":[],"attachments":[],"embeds":[{"title":"Sukces!","url":"","color":"RED","timestamp":"false","imageUrl":"","thumbUrl":"","description":"Reset bota  został **pomyślnie** przeprowadzony.","fields":[],"author":"","authorUrl":"","authorIcon":"","footerText":"","footerIconUrl":""}],"reply":true,"ephemeral":true,"tts":false,"overwrite":false,"dontSend":false,"editMessage":"0","editMessageVarName":"","storage":"0","varName2":"","name":"Send Message"},{"filename":"bot.js","name":"Restart Bot"}],"comType":"4","restriction":"2","permissions":"NONE","description":"Restart bota"},{"name":"status","permissions":"NONE","permissions2":"NONE","restriction":"1","_id":"ElYnz","actions":[{"member":"1","varName":"","info":"6","varName2":"","iftrue":"2","iftrueVal":"4","iffalse":"0","iffalseVal":"4","name":"Check If Member"},{"channel":"0","varName":"","message":"","buttons":[],"selectMenus":[],"attachments":[],"embeds":[{"title":"Niestety...","url":"","color":"RED","timestamp":"false","imageUrl":"","thumbUrl":"","description":"Tej komendy może używać tylko **właściciel** bota","fields":[],"author":"","authorUrl":"","authorIcon":"","footerText":"","footerIconUrl":""}],"reply":true,"ephemeral":true,"tts":false,"overwrite":false,"dontSend":false,"editMessage":"0","editMessageVarName":"","storage":"0","varName2":"","name":"Send Message"},{"name":"End Action Sequence"},{"storage":"4","varName":"StatusBota","branches":[{"comparison":"1","value":"1","actions":[{"title":"Status","textInputs":[{"name":"Jaki status?","placeholder":"np. Serwer itp","minLength":"0","maxLength":"1000","id":"Statusv1","row":"1","style":"PARAGRAPH","required":"true"}],"name":"Show Modal"},{"gameName":"${tempVars(\"Statusv1\")}","gameLink":"","activityType":"WATCHING","name":"Set Bot Game"},{"channel":"0","varName":"","message":"","buttons":[],"selectMenus":[],"attachments":[],"embeds":[{"title":"Sukces","url":"","color":"RED","timestamp":"false","imageUrl":"","thumbUrl":"","description":"Pomyślnie ustawiłem botowi status **Ogląda** `${tempVars(\"Statusv1\")}`","fields":[],"author":"","authorUrl":"","authorIcon":"","footerText":"","footerIconUrl":""}],"reply":true,"ephemeral":true,"tts":false,"overwrite":false,"dontSend":false,"editMessage":"0","editMessageVarName":"","storage":"0","varName2":"","name":"Send Message"}]},{"comparison":"1","value":"2","actions":[{"title":"Status","textInputs":[{"name":"Jaki status?","placeholder":"np. Serwer itp","minLength":"0","maxLength":"1000","id":"Statusv1","row":"1","style":"PARAGRAPH","required":"true"}],"name":"Show Modal"},{"gameName":"${tempVars(\"Statusv1\")}","gameLink":"","activityType":"PLAYING","name":"Set Bot Game"},{"channel":"0","varName":"","message":"","buttons":[],"selectMenus":[],"attachments":[],"embeds":[{"title":"Sukces","url":"","color":"RED","timestamp":"false","imageUrl":"","thumbUrl":"","description":"Pomyślnie ustawiłem botowi status **W grze** `${tempVars(\"Statusv1\")}`","fields":[],"author":"","authorUrl":"","authorIcon":"","footerText":"","footerIconUrl":""}],"reply":true,"ephemeral":true,"tts":false,"overwrite":false,"dontSend":false,"editMessage":"0","editMessageVarName":"","storage":"0","varName2":"","name":"Send Message"}]},{"comparison":"1","value":"4","actions":[{"title":"Status","textInputs":[{"name":"Jaki status?","placeholder":"np. Serwer itp","minLength":"0","maxLength":"1000","id":"Statusv1","row":"1","style":"PARAGRAPH","required":"true"}],"name":"Show Modal"},{"gameName":"${tempVars(\"Statusv1\")}","gameLink":"","activityType":"LISTENING","name":"Set Bot Game"},{"channel":"0","varName":"","message":"","buttons":[],"selectMenus":[],"attachments":[],"embeds":[{"title":"Sukces","url":"","color":"RED","timestamp":"false","imageUrl":"","thumbUrl":"","description":"Pomyślnie ustawiłem botowi status **Słucha** `${tempVars(\"Statusv1\")}`","fields":[],"author":"","authorUrl":"","authorIcon":"","footerText":"","footerIconUrl":""}],"reply":true,"ephemeral":true,"tts":false,"overwrite":false,"dontSend":false,"editMessage":"0","editMessageVarName":"","storage":"0","varName2":"","name":"Send Message"}]},{"comparison":"1","value":"5","actions":[{"title":"Status","textInputs":[{"name":"Jaki status?","placeholder":"np. Serwer itp","minLength":"0","maxLength":"1000","id":"Statusv1","row":"1","style":"PARAGRAPH","required":"true"}],"name":"Show Modal"},{"gameName":"${tempVars(\"Statusv1\")}","gameLink":"","activityType":"COMPETING","name":"Set Bot Game"},{"channel":"0","varName":"","message":"","buttons":[],"selectMenus":[],"attachments":[],"embeds":[{"title":"Sukces","url":"","color":"RED","timestamp":"false","imageUrl":"","thumbUrl":"","description":"Pomyślnie ustawiłem botowi status **Rywalizuje w** `${tempVars(\"Statusv1\")}`","fields":[],"author":"","authorUrl":"","authorIcon":"","footerText":"","footerIconUrl":""}],"reply":true,"ephemeral":true,"tts":false,"overwrite":false,"dontSend":false,"editMessage":"0","editMessageVarName":"","storage":"0","varName2":"","name":"Send Message"}]}],"name":"Multi-Check Variable"}],"comType":"4","parameters":[{"name":"StatusBota","description":"Jaki ustawić status?","type":"STRING","required":true,"choices":[{"name":"ogląda","value":"1"},{"name":"gra","value":"2"},{"name":"słucha","value":"4"},{"name":"rywalizuje","value":"5"}]}],"description":"Wybierz jaki ma mieć status bota!"},{"name":"tvpis","permissions":"NONE","permissions2":"NONE","restriction":"1","_id":"yNzCF","actions":[{"text":"${slashParams(\"tekst\")}","text2":" ","text3":"%20","info":"1","storage":"1","varName":"rep","name":"Replace Text"},{"server":"0","varName":"","info":"2","storage":"1","varName2":"nazwa-serw","name":"Store Server Info"},{"server":"0","varName":"","info":"5","storage":"1","varName2":"ikon-serw","name":"Store Server Info"},{"channel":"0","varName":"","message":"","buttons":[],"selectMenus":[],"attachments":[],"embeds":[{"title":"","url":"","color":"RED","timestamp":"true","imageUrl":"${\"http://api.wiedzminpolska.ml:6660/tvpis?tekst=\" + encodeURIComponent(tempVars(\"rep\"))}","thumbUrl":"","description":"","fields":[],"author":"","authorUrl":"","authorIcon":"","footerText":"${tempVars(\"nazwa-serw\")}","footerIconUrl":"${tempVars(\"ikon-serw\")}"}],"reply":true,"ephemeral":false,"tts":false,"overwrite":false,"dontSend":false,"editMessage":"0","editMessageVarName":"","storage":"0","varName2":"","name":"Send Message"}],"comType":"4","parameters":[{"name":"tekst","description":"Podaj tytuł paska","type":"STRING","required":true,"choices":null}],"description":"Pasek z wiadomości tvp"},{"name":"ankieta","permissions":"NONE","permissions2":"NONE","restriction":"1","_id":"mSQfG","actions":[{"member":"1","varName":"","permission":"ADMINISTRATOR","branch":{"iftrue":"3","iffalse":"0","iftrueVal":"2"},"name":"Check Member Permissions"},{"channel":"0","varName":"","message":"","buttons":[],"selectMenus":[],"attachments":[],"embeds":[{"title":"Błąd!","url":"","color":"RED","timestamp":"false","imageUrl":"","thumbUrl":"","description":"> `❌` Nie masz wystarczających uprawnień!\n> `🔒` Uprawnienie - **Administrator**","fields":[],"author":"","authorUrl":"","authorIcon":"","footerText":"","footerIconUrl":""}],"reply":true,"ephemeral":true,"tts":false,"overwrite":false,"dontSend":false,"editMessage":"0","editMessageVarName":"","storage":"0","varName2":"","name":"Send Message"},{"name":"End Action Sequence"},{"server":"0","varName":"","info":"2","storage":"1","varName2":"nazwa_serwer","name":"Store Server Info"},{"server":"0","varName":"","info":"5","storage":"1","varName2":"ikon_serwer","name":"Store Server Info"},{"channel":"0","varName":"","message":"","buttons":[],"selectMenus":[],"attachments":[],"embeds":[{"title":"Nowa ankieta!","url":"","color":"RED","timestamp":"true","imageUrl":"","thumbUrl":"","description":"","fields":[{"name":"**Treść:**","value":"***${slashParams(\"Treść\")}***","inline":"false"}],"author":"","authorUrl":"","authorIcon":"","footerText":"${tempVars(\"nazwa_serwer\")}","footerIconUrl":"${tempVars(\"ikon_serwer\")}"}],"reply":true,"ephemeral":false,"tts":false,"overwrite":false,"dontSend":false,"editMessage":"0","editMessageVarName":"","storage":"1","varName2":"Kaczkajta","name":"Send Message"},{"storage":"1","varName":"Kaczkajta","emoji":"4","varName2":"👍","varName3":"","name":"Add Reaction"},{"storage":"1","varName":"Kaczkajta","emoji":"4","varName2":"👎","varName3":"","name":"Add Reaction"}],"comType":"4","description":"Zadawaj pytania","parameters":[{"name":"Treść","description":"treść ankiety","type":"STRING","required":true,"choices":null}]},{"name":"podanie","permissions":"BAN_MEMBERS","permissions2":"NONE","restriction":"1","_id":"PJNND","actions":[{"channel":"0","varName":"","message":"","buttons":[{"name":"Utwórz podanie!","type":"PRIMARY","id":"podanie.setup.dbm","row":"","url":"","emoji":"","mode":"PERSISTENT","time":"","actions":[{"member":"1","varName":"","info":"1","storage":"1","varName2":"button.member","name":"Store Member Info"},{"member":"1","varName":"","info":"31","storage":"1","varName2":"button.avatarurl","name":"Store Member Info"},{"member":"1","varName":"","info":"22","storage":"1","varName2":"button.utworzenie","name":"Store Member Info"},{"member":"1","varName":"","info":"2","storage":"1","varName2":"button.username","name":"Store Member Info"},{"member":"1","varName":"","info":"20","storage":"1","varName2":"button.tag","name":"Store Member Info"},{"title":"Aston Villa F.C.","textInputs":[{"name":"Imie:","placeholder":"","minLength":"0","maxLength":"100","id":"1","row":"","style":"SHORT","required":"true"},{"name":"Nazwisko","placeholder":"","minLength":"0","maxLength":"100","id":"2","row":"","style":"SHORT","required":"true"},{"name":"Wiek:","placeholder":"","minLength":"0","maxLength":"100","id":"3","row":"","style":"SHORT","required":"true"},{"name":"Na jakiej pozycji grasz?:","placeholder":"","minLength":"0","maxLength":"100","id":"4","row":"","style":"SHORT","required":"true"}],"name":"Show Modal"},{"channel":"0","varName":"","message":"","buttons":[],"selectMenus":[],"attachments":[],"embeds":[{"title":"Twoje podanie zostało wysłane!","url":"","color":"GREEN","timestamp":"false","imageUrl":"","thumbUrl":"","description":"Dziękujemy za uzupełnianie formularzu, oczekuj odpowiedzi!","fields":[],"author":"","authorUrl":"","authorIcon":"","footerText":"","footerIconUrl":""}],"reply":true,"ephemeral":true,"tts":false,"overwrite":false,"dontSend":false,"editMessage":"0","editMessageVarName":"","storage":"0","varName2":"","name":"Send Message"},{"channel":"103","varName":"1051226307507277824","message":"","buttons":[],"selectMenus":[],"attachments":[],"embeds":[{"title":"","url":"","color":"#42f5b9","timestamp":"false","imageUrl":"","thumbUrl":"${tempVars(\"button.avatarurl\")}","description":"> [INFORMACJE O OSOBIE](https://discoid.cc/${tempVars(\"button.member\")})\n\n> **Data utworzenia konta discord:** ${tempVars(\"button.utworzenie\")}\n\n> **OPCJA 1:** ${tempVars(\"1\")}\n\n> **OPCJA 2:** ${tempVars(\"2\")}\n\n> **OPCJA 3:** ${tempVars(\"3\")}\n\n> **OPCJA 4:** ${tempVars(\"4\")}\n","fields":[],"author":"Podanie ${tempVars(\"button.username\")}#${tempVars(\"button.tag\")}","authorUrl":"","authorIcon":"","footerText":"","footerIconUrl":""}],"reply":true,"ephemeral":false,"tts":false,"overwrite":false,"dontSend":false,"editMessage":"0","editMessageVarName":"","storage":"0","varName2":"","name":"Send Message"},{"channel":"103","varName":"1051226307507277824","message":"@everyone","buttons":[],"selectMenus":[],"attachments":[],"embeds":[],"reply":true,"ephemeral":false,"tts":false,"overwrite":false,"dontSend":false,"editMessage":"0","editMessageVarName":"","storage":"0","varName2":"","name":"Send Message"}]}],"selectMenus":[],"attachments":[],"embeds":[{"title":"","url":"","color":"#5286ff","timestamp":"false","imageUrl":"","thumbUrl":"","description":"**IC (In Character)**\n`《😍》`Imię:\n`《💘》`Nazwisko:\n`《🍓》`Wiek:\n`《🏍》`Na jakiej pozycji grasz?:","fields":[],"author":"Wzór","authorUrl":"","authorIcon":"","footerText":"","footerIconUrl":""}],"reply":false,"ephemeral":false,"tts":false,"overwrite":false,"dontSend":false,"editMessage":"0","editMessageVarName":"","storage":"0","varName2":"","name":"Send Message"}],"comType":"4","description":"Podanie"},{"name":"dodaj","permissions":"MANAGE_MESSAGES","permissions2":"NONE","restriction":"1","_id":"RqvLT","actions":[{"member":"5","varName":"Użytkownik","info":"16","storage":"1","varName2":"AvURL","name":"Store Member Info"},{"channel":"0","varName":"","message":"","buttons":[],"selectMenus":[],"attachments":[],"embeds":[{"title":"DOSTĘP","url":"","color":"BLUE","timestamp":"false","imageUrl":"${tempVars(\"AvURL\")}","thumbUrl":"","description":"Nadano permisje `druzyna`\nNadawca: ${member}\nUżytkownik: ${slashParams(\"Użytkownik\")}","fields":[],"author":"","authorUrl":"","authorIcon":"","footerText":"${slashParams(\"Użytkownik\")}","footerIconUrl":"${tempVars(\"AvURL\")}"}],"reply":true,"ephemeral":false,"tts":false,"overwrite":false,"dontSend":false,"editMessage":"0","editMessageVarName":"","storage":"0","varName2":"","name":"Send Message"},{"member":"5","varName2":"Użytkownik","role":"101","varName":"1051223801532268555","reason":"","name":"Add Member Role"},{"channel":"103","varName":"1051219942273462354","message":"**${slashParams(\"Użytkownik\")}** dostał się do drużyny!\n","buttons":[],"selectMenus":[],"attachments":[],"embeds":[],"reply":true,"ephemeral":false,"tts":false,"overwrite":false,"dontSend":false,"editMessage":"0","editMessageVarName":"","storage":"0","varName2":"","name":"Send Message"},{"role":"101","varName":"1051223801532268555","info":"12","storage":"1","varName2":"liczba","name":"Store Role Info"},{"storage":"101","varName":"1051498846204743791","channelType":"1","toChange":"0","newState":"﹝🤩﹞Klub : ${tempVars(\"liczba\")}","name":"Edit Channel"}],"comType":"4","description":"Dodaje do teamu","parameters":[{"name":"Użytkownik","description":"Kto ma dostać range?","type":"USER","required":true,"choices":null}]},{"name":"weryfikacja","permissions":"NONE","permissions2":"NONE","restriction":"1","_id":"UEAUw","actions":[{"channel":"0","varName":"","message":"","buttons":[{"name":"🖤","type":"SUCCESS","id":"msg-button-52237f6","row":"","url":"","emoji":"","mode":"PERSISTENT","time":"","actions":[{"member":"1","varName2":"","role":"101","varName":"1051224097750786128","reason":"","name":"Add Member Role"}]}],"selectMenus":[],"attachments":[],"embeds":[{"title":"WERYFIKACJA","url":"","color":"GREEN","timestamp":"false","imageUrl":"","thumbUrl":"","description":"Kliknij w guzik👇","fields":[],"author":"","authorUrl":"","authorIcon":"","footerText":"","footerIconUrl":""}],"reply":false,"ephemeral":false,"tts":false,"overwrite":false,"dontSend":false,"editMessage":"0","editMessageVarName":"","storage":"0","varName2":"","name":"Send Message"}],"comType":"4","parameters":[]},{"name":"pochwała","permissions":"ADMINISTRATOR","permissions2":"NONE","restriction":"1","_id":"cUTgA","actions":[{"channel":"0","varName":"","message":"","buttons":[],"selectMenus":[],"attachments":[],"embeds":[{"title":"POCHWAŁA","url":"","color":"GREEN","timestamp":"false","imageUrl":"","thumbUrl":"","description":"Pochwałe dostał: **${slashParams(\"Kto\")}**\nOpis:\n**${slashParams(\"Opis\")}**","fields":[],"author":"","authorUrl":"","authorIcon":"","footerText":"${member.displayName} - ${slashParams(\"Kto\")}","footerIconUrl":""}],"reply":true,"ephemeral":false,"tts":false,"overwrite":false,"dontSend":false,"editMessage":"0","editMessageVarName":"","storage":"0","varName2":"","name":"Send Message"},{"channel":"103","varName":"1051882599284482068","message":"","buttons":[],"selectMenus":[],"attachments":[],"embeds":[{"title":"POCHWAŁA","url":"","color":"GREEN","timestamp":"false","imageUrl":"","thumbUrl":"","description":"Pochwałe dostał: **${slashParams(\"Kto\")}**\nOpis:\n**${slashParams(\"Opis\")}**","fields":[],"author":"","authorUrl":"","authorIcon":"","footerText":"${member.displayName} - ${slashParams(\"Kto\")}","footerIconUrl":""}],"reply":true,"ephemeral":false,"tts":false,"overwrite":false,"dontSend":false,"editMessage":"0","editMessageVarName":"","storage":"0","varName2":"","name":"Send Message"}],"comType":"4","parameters":[{"name":"Kto","description":"Kto?","type":"USER","required":true,"choices":null},{"name":"Opis","description":"Opis pochwały","type":"STRING","required":true,"choices":null}]}]